setuphelpers.py
setuphelpers-0.1.2.dist-info/DESCRIPTION.rst
setuphelpers-0.1.2.dist-info/METADATA
setuphelpers-0.1.2.dist-info/RECORD
setuphelpers-0.1.2.dist-info/WHEEL
setuphelpers-0.1.2.dist-info/metadata.json
setuphelpers-0.1.2.dist-info/top_level.txt
