Metadata-Version: 2.0
Name: setuphelpers
Version: 0.1.2
Summary: Setuptools helper functions
Home-page: https://github.com/ccpgames/setuphelpers/
Author: Adam Talsma
Author-email: se-adam.talsma@ccpgames.com
License: UNKNOWN
Download-URL: https://github.com/ccpgames/setuphelpers/
Platform: UNKNOWN
Classifier: Development Status :: 2 - Pre-Alpha
Classifier: Operating System :: POSIX :: Linux
Classifier: License :: OSI Approved :: MIT License
Classifier: Programming Language :: Python :: 3
Classifier: Topic :: Software Development
Classifier: Topic :: System :: Archiving :: Packaging
Classifier: Topic :: Utilities
